nextrows/__init__.py
nextrows/client.py
nextrows/types.py
nextrows/api/apps.py
nextrows/api/credits.py
nextrows/api/extract.py
nextrows_py-0.1.0.dist-info/licenses/LICENSE.md
nextrows_py-0.1.0.dist-info/METADATA
nextrows_py-0.1.0.dist-info/WHEEL
nextrows_py-0.1.0.dist-info/top_level.txt
nextrows_py-0.1.0.dist-info/RECORD
