Metadata-Version: 2.4
Name: nextrows-py
Version: 0.1.0
Summary: Python client for the Nextrows Open API.
Author: workbricksai
License: MIT License
Project-URL: Homepage, https://nextrows.com
Project-URL: Documentation, https://nextrows.com/docs/api
Project-URL: Repository, https://nextrows.com
Keywords: nextrows,api,client
Classifier: Development Status :: 3 - Alpha
Classifier: License :: OSI Approved :: MIT License
Classifier: Programming Language :: Python :: 3
Classifier: Programming Language :: Python :: 3.8
Classifier: Programming Language :: Python :: 3.9
Classifier: Programming Language :: Python :: 3.10
Classifier: Programming Language :: Python :: 3.11
Classifier: Programming Language :: Python :: 3.12
Classifier: Operating System :: OS Independent
Requires-Python: >=3.8
License-File: LICENSE.md
Requires-Dist: requests>=2.31
Requires-Dist: typing-extensions>=4.7
Provides-Extra: schema
Requires-Dist: pydantic>=1.10; extra == "schema"
Provides-Extra: async
Requires-Dist: httpx>=0.24; extra == "async"
Provides-Extra: test
Requires-Dist: pytest>=7.4; extra == "test"
Dynamic: license-file
